django_org/__init__.py
django_org/admin.py
django_org/apps.py
django_org/const.py
django_org/exceptions.py
django_org/forms.py
django_org/models.py
django_org/settings.py
django_org/urls.py
django_org/utils.py
django_org/locale/en/LC_MESSAGES/django.mo
django_org/locale/en/LC_MESSAGES/django.po
django_org/locale/es/LC_MESSAGES/django.mo
django_org/locale/es/LC_MESSAGES/django.po
django_org/locale/ru/LC_MESSAGES/django.mo
django_org/locale/ru/LC_MESSAGES/django.po
django_org/migrations/0001_initial.py
django_org/migrations/__init__.py
django_org-0.2.0.dist-info/LICENSE
django_org-0.2.0.dist-info/METADATA
django_org-0.2.0.dist-info/WHEEL
django_org-0.2.0.dist-info/top_level.txt
django_org-0.2.0.dist-info/RECORD
