Metadata-Version: 2.1
Name: django-org
Version: 0.2.0
Summary: Base classes for enterprise modeling
Home-page: https://github.com/pikhovkin/django-org
Author: Sergei Pikhovkin
Author-email: s@pikhovkin.ru
License: MIT
Keywords: django,enterprise,organization,regime,shift,work mode,work regime,work shift
Classifier: Development Status :: 3 - Alpha
Classifier: Environment :: Web Environment
Classifier: Framework :: Django :: 3.1
Classifier: Framework :: Django :: 3.2
Classifier: Framework :: Django :: 4.0
Classifier: Framework :: Django :: 4.1
Classifier: Intended Audience :: Developers
Classifier: License :: OSI Approved :: MIT License
Classifier: Operating System :: OS Independent
Classifier: Programming Language :: Python :: 3 :: Only
Classifier: Programming Language :: Python :: 3.9
Classifier: Programming Language :: Python :: 3.10
Classifier: Programming Language :: Python :: 3.11
Requires-Python: >=3.9.*, <4.2.*
License-File: LICENSE
Requires-Dist: Django (<4.2,>=3.1)
Provides-Extra: all
Requires-Dist: Django (<4.2,>=3.1) ; extra == 'all'
Requires-Dist: django-easy-select2 ; extra == 'all'
Provides-Extra: select2
Requires-Dist: django-easy-select2 ; extra == 'select2'
